[{"model": "rabbits.rabbit", "pk": 1, "fields": {"name": "Miffy", "breed": "Flemish Giant", "sex": "F", "date_of_birth": "2018-12-30", "description": "A lovely rabbit", "neutered": true, "vaccinated": true, "group": 1}}, {"model": "rabbits.rabbit", "pk": 2, "fields": {"name": "Olive", "breed": "Netherland Dwarf", "sex": "M", "date_of_birth": "2024-11-16", "description": "A lovely rabbit", "neutered": true, "vaccinated": true, "group": 1}}, {"model": "rabbits.rabbit", "pk": 3, "fields": {"name": "Thumper", "breed": "Flemish Giant", "sex": "M", "date_of_birth": "2024-12-20", "description": "A lovely rabbit", "neutered": true, "vaccinated": false, "group": 2}}, {"model": "rabbits.rabbit", "pk": 4, "fields": {"name": "Cinnabun", "breed": "Flemish Giant", "sex": "F", "date_of_birth": "2020-02-01", "description": "A lovely rabbit", "neutered": false, "vaccinated": false, "group": 3}}, {"model": "rabbits.rabbit", "pk": 5, "fields": {"name": "Daisy", "breed": "Angora", "sex": "M", "date_of_birth": "2018-11-12", "description": "A lovely rabbit", "neutered": true, "vaccinated": true, "group": 4}}, {"model": "rabbits.rabbit", "pk": 6, "fields": {"name": "Brno", "breed": "Mini Lop", "sex": "F", "date_of_birth": "2014-12-10", "description": "A lovely rabbit", "neutered": false, "vaccinated": false, "group": 5}}, {"model": "rabbits.rabbit", "pk": 7, "fields": {"name": "Tom", "breed": "English Lop", "sex": "M", "date_of_birth": "2011-10-17", "description": "A lovely rabbit", "neutered": true, "vaccinated": true, "group": 5}}, {"model": "rabbits.rabbit", "pk": 8, "fields": {"name": "Holly", "breed": "Netherland Dwarf", "sex": "F", "date_of_birth": "2016-05-12", "description": "A lovely rabbit", "neutered": false, "vaccinated": true, "group": 6}}, {"model": "rabbits.rabbit", "pk": 9, "fields": {"name": "Oreo", "breed": "Mini Lop", "sex": "M", "date_of_birth": "2014-10-03", "description": "A lovely rabbit", "neutered": true, "vaccinated": true, "group": 7}}, {"model": "rabbits.rabbit", "pk": 10, "fields": {"name": "Lola", "breed": "Flemish Giant", "sex": "M", "date_of_birth": "2023-11-23", "description": "A lovely rabbit", "neutered": false, "vaccinated": true, "group": 8}}, {"model": "rabbits.rabbit", "pk": 11, "fields": {"name": "Chester", "breed": "Mini Lop", "sex": "F", "date_of_birth": "2012-07-01", "description": "A lovely rabbit", "neutered": false, "vaccinated": true, "group": 9}}, {"model": "rabbits.rabbit", "pk": 12, "fields": {"name": "Snowball", "breed": "English Lop", "sex": "F", "date_of_birth": "2016-03-08", "description": "A lovely rabbit", "neutered": false, "vaccinated": true, "group": 10}}, {"model": "rabbits.rabbit", "pk": 13, "fields": {"name": "Hopper", "breed": "English Lop", "sex": "M", "date_of_birth": "2018-06-26", "description": "A lovely rabbit", "neutered": false, "vaccinated": true, "group": 11}}, {"model": "rabbits.rabbit", "pk": 14, "fields": {"name": "Jack", "breed": "Mini Lop", "sex": "F", "date_of_birth": "2021-10-18", "description": "A lovely rabbit", "neutered": true, "vaccinated": true, "group": 12}}, {"model": "rabbits.rabbit", "pk": 15, "fields": {"name": "Jill", "breed": "Mini Lop", "sex": "M", "date_of_birth": "2020-07-23", "description": "A lovely rabbit", "neutered": false, "vaccinated": true, "group": 12}}, {"model": "rabbits.rabbit", "pk": 16, "fields": {"name": "Fish", "breed": "Lionhead", "sex": "F", "date_of_birth": "2011-02-24", "description": "A lovely rabbit", "neutered": true, "vaccinated": false, "group": 13}}, {"model": "rabbits.rabbit", "pk": 17, "fields": {"name": "Chips", "breed": "Netherland Dwarf", "sex": "F", "date_of_birth": "2014-11-03", "description": "A lovely rabbit", "neutered": true, "vaccinated": true, "group": 13}}, {"model": "rabbits.rabbit", "pk": 18, "fields": {"name": "Oliver", "breed": "Flemish Giant", "sex": "M", "date_of_birth": "2019-12-31", "description": "A lovely rabbit", "neutered": true, "vaccinated": true, "group": 14}}, {"model": "rabbits.rabbit", "pk": 19, "fields": {"name": "Fluff", "breed": "Netherland Dwarf", "sex": "F", "date_of_birth": "2019-12-26", "description": "A lovely rabbit", "neutered": false, "vaccinated": true, "group": 15}}, {"model": "rabbits.rabbit", "pk": 20, "fields": {"name": "Bunbun", "breed": "English Lop", "sex": "F", "date_of_birth": "2015-06-28", "description": "A lovely rabbit", "neutered": true, "vaccinated": true, "group": 15}}, {"model": "rabbits.rabbit", "pk": 21, "fields": {"name": "Teddy", "breed": "Flemish Giant", "sex": "M", "date_of_birth": "2021-11-05", "description": "A lovely rabbit", "neutered": true, "vaccinated": true, "group": 16}}]